yookassa_api/__init__.py
yookassa_api/__meta__.py
yookassa_api/api/__init__.py
yookassa_api/api/base.py
yookassa_api/api/client.py
yookassa_api/api/methods.py
yookassa_api/exceptions/__init__.py
yookassa_api/exceptions/base.py
yookassa_api/exceptions/common.py
yookassa_api/exceptions/unauthorized.py
yookassa_api/schemas.py
yookassa_api/types.py
yookassa_api-0.3.5.dist-info/LICENSE
yookassa_api-0.3.5.dist-info/METADATA
yookassa_api-0.3.5.dist-info/WHEEL
yookassa_api-0.3.5.dist-info/RECORD
