Metadata-Version: 2.3
Name: yookassa_api
Version: 0.3.5
Summary: Python Library for YooKassa API
License: MIT
Author: Lems0n
Author-email: abdulla.dev@mail.ru
Requires-Python: >=3.10
Classifier: License :: OSI Approved :: MIT License
Classifier: Programming Language :: Python :: 3
Classifier: Programming Language :: Python :: 3.10
Classifier: Programming Language :: Python :: 3.11
Classifier: Programming Language :: Python :: 3.12
Classifier: Programming Language :: Python :: 3.13
Requires-Dist: aiohttp (>=3.11.11,<4.0.0)
Requires-Dist: pydantic (>=2.10.5,<3.0.0)
Requires-Dist: requests (>=2.32.3,<3.0.0)
